heksher/__init__.py
heksher/_version.py
heksher/clients/__init__.py
heksher/clients/async_client.py
heksher/clients/stub.py
heksher/clients/subclasses.py
heksher/clients/thread_client.py
heksher/clients/util.py
heksher/exceptions.py
heksher/heksher_client.py
heksher/main_client.py
heksher/setting.py
heksher/setting_type.py
heksher/util.py
heksher-0.2.2.dist-info/LICENSE
heksher-0.2.2.dist-info/METADATA
heksher-0.2.2.dist-info/WHEEL
heksher-0.2.2.dist-info/RECORD
