Metadata-Version: 2.1
Name: heksher
Version: 0.2.2
Summary: 
Home-page: https://github.com/biocatchltd/heksher-py
License: MIT
Author: Biocatch LTD
Author-email: serverteam@biocatch.com
Requires-Python: >=3.7,<4.0
Classifier: License :: OSI Approved :: MIT License
Classifier: Programming Language :: Python :: 3
Classifier: Programming Language :: Python :: 3.7
Classifier: Programming Language :: Python :: 3.8
Classifier: Programming Language :: Python :: 3.9
Classifier: Programming Language :: Python :: 3.10
Classifier: Programming Language :: Python :: 3.11
Requires-Dist: Deprecated (>=1.2.13)
Requires-Dist: httpx
Requires-Dist: mock (>=4.0.0,<5.0.0) ; python_version < "3.8"
Requires-Dist: ordered-set (>=4.0.0,<5.0.0)
Requires-Dist: orjson (>=3.0.0)
Requires-Dist: pydantic (>=1.0.0,<2.0.0)
Requires-Dist: sortedcontainers (>=2.4.0,<3.0.0)
Project-URL: Repository, https://github.com/biocatchltd/heksher-py
